octoprint_factor_plugin-2.5.5.dist-info/licenses/LICENSE
octoprint_mqtt/__init__.py
octoprint_mqtt/control.py
octoprint_mqtt/mqtt_gcode.py
octoprint_mqtt/static/css/mqtt.css
octoprint_mqtt/static/js/i18n.js
octoprint_mqtt/static/js/mqtt.js
octoprint_mqtt/static/translations/en.json
octoprint_mqtt/static/translations/ko.json
octoprint_mqtt/templates/mqtt_settings.jinja2
octoprint_mqtt/templates/mqtt_wizard.jinja2
octoprint_factor_plugin-2.5.5.dist-info/METADATA
octoprint_factor_plugin-2.5.5.dist-info/WHEEL
octoprint_factor_plugin-2.5.5.dist-info/entry_points.txt
octoprint_factor_plugin-2.5.5.dist-info/top_level.txt
octoprint_factor_plugin-2.5.5.dist-info/RECORD
