Metadata-Version: 2.4
Name: octoprint-factor-plugin
Version: 2.5.5
Summary: FACTOR Plugin - Remote monitoring and camera integration for OctoPrint
Home-page: https://github.com/kangbyounggwan/octoprint-factor-plugin
Author: FACTOR
Author-email: FACTOR Team <tlvh109@gmail.com>
License: AGPLv3
Project-URL: Homepage, https://factor.io.kr
Project-URL: Repository, https://github.com/kangbyounggwan/octoprint-factor-plugin
Project-URL: Issues, https://github.com/kangbyounggwan/octoprint-factor-plugin/issues
Keywords: octoprint,plugin,3dprinting,mqtt,monitoring,camera
Classifier: Development Status :: 4 - Beta
Classifier: Intended Audience :: End Users/Desktop
Classifier: License :: OSI Approved :: GNU Affero General Public License v3
Classifier: Natural Language :: English
Classifier: Natural Language :: Korean
Classifier: Operating System :: OS Independent
Classifier: Programming Language :: Python :: 3
Classifier: Programming Language :: Python :: 3.8
Classifier: Programming Language :: Python :: 3.9
Classifier: Programming Language :: Python :: 3.10
Classifier: Programming Language :: Python :: 3.11
Classifier: Programming Language :: Python :: 3.12
Classifier: Topic :: System :: Monitoring
Classifier: Topic :: Printing
Requires-Python: >=3.8,<4
License-File: LICENSE
Requires-Dist: OctoPrint>=1.4.0
Requires-Dist: paho-mqtt>=2.0.0
Dynamic: author
Dynamic: home-page
Dynamic: license-file
Dynamic: requires-python
